swanapi/__init__.py
swanapi/base_inference.py
swanapi/base_requests.py
swanapi/make_build.py
swanapi/server.py
swanapi/swan_types.py
swanapi/docker_builder/__init__.py
swanapi/docker_builder/config.py
swanapi/docker_builder/cuda_container.py
swanapi/docker_builder/generate_dockerfile.py
swanapi/docker_builder/runner.py
swanapi/utils/__init__.py
swanapi/utils/utils.py
swanapi-0.2.5.dist-info/METADATA
swanapi-0.2.5.dist-info/WHEEL
swanapi-0.2.5.dist-info/entry_points.txt
swanapi-0.2.5.dist-info/top_level.txt
swanapi-0.2.5.dist-info/RECORD
