Metadata-Version: 2.1
Name: swanapi
Version: 0.2.5
Summary: A low threshold, high performance, compatible with a variety of different scenarios of deep learning API image construction and reasoning tool
Author: ZeYiLin
Author-email: zeyi.lin@swanhub.co
Requires-Dist: flask
Requires-Dist: PyYAML
Requires-Dist: pillow
Requires-Dist: numpy
Requires-Dist: nvidia-ml-py
